cloudcode.py
sandbox_line.py
stream.py
cloudcode-0.0.7.dist-info/METADATA
cloudcode-0.0.7.dist-info/WHEEL
cloudcode-0.0.7.dist-info/top_level.txt
cloudcode-0.0.7.dist-info/RECORD
