Metadata-Version: 2.4
Name: cloudcode
Version: 0.0.7
Summary: Code the thing that Codes the thing
Author: Sean Sullivan
Author-email: Sean Sullivan <sean@lmsystems.ai>
License: MIT
Project-URL: Homepage, https://cloudcode.ai
Requires-Python: >=3.10
Requires-Dist: aider-chat>=0.82.1
Requires-Dist: e2b-code-interpreter>=1.2.1
Dynamic: author
Dynamic: requires-python
